{
    "status":0,
    "message":[
        {
            "company": "生益科技",
            "stockCode": "(600183)",
            "situation": "资金流入，趋势向上",
            "star":5,
            "precent": "50.00%",
            "line": "中线",
            "descCode": "近期持续有大单买入且资金流入的股票，经过充分的换手以后，股价会有阶段性的良好表现",
            "two": {
                "name01": "跳空高开",
                "count01": "25.83",
                "data01": "-1.96%",

                "name02": "短线上涨",
                "count02": "24.84",
                "data02": "+0.57%"
            }
        },
        {
            "company": "起帆电缆",
            "stockCode": "(605222)",
            "situation": "稳健增值蓝筹股",
            "star":5,
            "precent": "53.91%",
            "line": "超短线",
            "descCode": "股价开盘强势上涨，资金大量流入且换手率控制在合理范围内，短线买方力量更强，股价上涨概率高。",
            "two": {
                "name01": "策略成功率",
                "count01": "32.45",
                "data01": "-1.01%",

                "name02": "年化收益率",
                "count02": "28.44",
                "data02": "+0.56%"
            }
        },
        {
            "company": "岳阳林纸",
            "stockCode": "(600963)",
            "situation": "均线多头，布林突破",
            "star":4,
            "precent": "56.03%",
            "line": "中线",
            "descCode": "公司业绩稳定，股价上涨波动较小，投资风险较低，适合中期持有",
            "two": {
                "name01": "跳水盘点",
                "count01": "23.58",
                "data01": "-0.45%",

                "name02": "均价上升",
                "count02": "12.83",
                "data02": "+1.37%"
            }
        }
    ]
}